ranstring/__init__.py
ranstring/gen.py
RanString-1.0.1.dist-info/LICENSE
RanString-1.0.1.dist-info/METADATA
RanString-1.0.1.dist-info/WHEEL
RanString-1.0.1.dist-info/top_level.txt
RanString-1.0.1.dist-info/RECORD
