Metadata-Version: 2.1
Name: RanString
Version: 1.0.1
Summary: A module to generate random strings of numbers and letters
Author: AndysThings
Author-email: andrew@andysthings.tk
License: UNKNOWN
Platform: UNKNOWN
Classifier: Programming Language :: Python :: 3
Classifier: License :: OSI Approved :: MIT License
Classifier: Operating System :: OS Independent
Requires-Python: >=3.7
License-File: LICENSE
